{
  "room_size": [
    6,
    6
  ],
  "screen_size": [
    512,
    512
  ],
  "seed": 418,
  "min_distance": 0.3,
  "objects": [
    {
      "object_id": 2132015,
      "model": "wood_chair",
      "name": "yellow chair",
      "pos": {
        "x": 1.0,
        "y": 0,
        "z": 2.0
      },
      "rot": {
        "x": 0,
        "y": 0,
        "z": 0
      },
      "size": [
        0.4298932,
        0.47789539999999997
      ],
      "attributes": {
        "scale": 1.0,
        "has_orientation": true,
        "color": {
          "name": "yellow",
          "r": 1.0,
          "g": 1.0,
          "b": 0.0,
          "a": 1.0
        },
        "orientation": "north"
      }
    },
    {
      "object_id": 5074546,
      "model": "ligne_roset_armchair",
      "name": "black chair",
      "pos": {
        "x": -1.0,
        "y": 0,
        "z": 2.0
      },
      "rot": {
        "x": 0,
        "y": 270,
        "z": 0
      },
      "size": [
        0.8185906,
        1.4368143
      ],
      "attributes": {
        "scale": 1.0,
        "has_orientation": true,
        "color": {
          "name": "black",
          "r": 0.0,
          "g": 0.0,
          "b": 0.0,
          "a": 1.0
        },
        "orientation": "west"
      }
    },
    {
      "object_id": 7556220,
      "model": "kettle",
      "name": "kettle",
      "pos": {
        "x": -1,
        "y": 0,
        "z": -1
      },
      "rot": {
        "x": 0,
        "y": 270,
        "z": 0
      },
      "size": [
        0.381692628,
        0.26722544400000003
      ],
      "attributes": {
        "scale": 1.8,
        "has_orientation": false
      }
    }
  ],
  "cameras": [
    {
      "id": "agent",
      "label": "A",
      "position": {
        "x": 0,
        "y": 0.8,
        "z": -1
      },
      "rotation": {
        "y": 0.0
      }
    },
    {
      "id": "2132015",
      "label": "1",
      "position": {
        "x": 1.0,
        "y": 0.8,
        "z": 2.0
      },
      "rotation": {
        "y": -153.434948822922
      }
    },
    {
      "id": "5074546",
      "label": "2",
      "position": {
        "x": -1.0,
        "y": 0.8,
        "z": 2.0
      },
      "rotation": {
        "y": 153.434948822922
      }
    },
    {
      "id": "7556220",
      "label": "3",
      "position": {
        "x": -1,
        "y": 0.8,
        "z": -1
      },
      "rotation": {
        "y": 45.0
      }
    }
  ],
  "images": [
    {
      "file": "agent_facing_north.png",
      "cam_id": "agent",
      "pos": {
        "x": 0,
        "y": 0.8,
        "z": -1
      },
      "direction": "north",
      "object_ratios": [
        {
          "object_id": 2132015,
          "model": "wood_chair",
          "visibility_ratio": 1.0,
          "occlusion_ratio": 1.0
        },
        {
          "object_id": 5074546,
          "model": "ligne_roset_armchair",
          "visibility_ratio": 1.0,
          "occlusion_ratio": 1.0
        }
      ]
    },
    {
      "file": "agent_facing_east.png",
      "cam_id": "agent",
      "pos": {
        "x": 0,
        "y": 0.8,
        "z": -1
      },
      "direction": "east",
      "object_ratios": []
    },
    {
      "file": "agent_facing_south.png",
      "cam_id": "agent",
      "pos": {
        "x": 0,
        "y": 0.8,
        "z": -1
      },
      "direction": "south",
      "object_ratios": []
    },
    {
      "file": "agent_facing_west.png",
      "cam_id": "agent",
      "pos": {
        "x": 0,
        "y": 0.8,
        "z": -1
      },
      "direction": "west",
      "object_ratios": [
        {
          "object_id": 7556220,
          "model": "kettle",
          "visibility_ratio": 1.0,
          "occlusion_ratio": 1.0
        }
      ]
    },
    {
      "file": "2132015_facing_north.png",
      "cam_id": "2132015",
      "pos": {
        "x": 1.0,
        "y": 0.8,
        "z": 2.0
      },
      "direction": "north",
      "object_ratios": []
    },
    {
      "file": "2132015_facing_east.png",
      "cam_id": "2132015",
      "pos": {
        "x": 1.0,
        "y": 0.8,
        "z": 2.0
      },
      "direction": "east",
      "object_ratios": []
    },
    {
      "file": "2132015_facing_south.png",
      "cam_id": "2132015",
      "pos": {
        "x": 1.0,
        "y": 0.8,
        "z": 2.0
      },
      "direction": "south",
      "object_ratios": [
        {
          "object_id": 7556220,
          "model": "kettle",
          "visibility_ratio": 1.0,
          "occlusion_ratio": 1.0
        }
      ]
    },
    {
      "file": "2132015_facing_west.png",
      "cam_id": "2132015",
      "pos": {
        "x": 1.0,
        "y": 0.8,
        "z": 2.0
      },
      "direction": "west",
      "object_ratios": [
        {
          "object_id": 5074546,
          "model": "ligne_roset_armchair",
          "visibility_ratio": 1.0,
          "occlusion_ratio": 1.0
        }
      ]
    },
    {
      "file": "5074546_facing_north.png",
      "cam_id": "5074546",
      "pos": {
        "x": -1.0,
        "y": 0.8,
        "z": 2.0
      },
      "direction": "north",
      "object_ratios": []
    },
    {
      "file": "5074546_facing_east.png",
      "cam_id": "5074546",
      "pos": {
        "x": -1.0,
        "y": 0.8,
        "z": 2.0
      },
      "direction": "east",
      "object_ratios": [
        {
          "object_id": 2132015,
          "model": "wood_chair",
          "visibility_ratio": 1.0,
          "occlusion_ratio": 1.0
        }
      ]
    },
    {
      "file": "5074546_facing_south.png",
      "cam_id": "5074546",
      "pos": {
        "x": -1.0,
        "y": 0.8,
        "z": 2.0
      },
      "direction": "south",
      "object_ratios": [
        {
          "object_id": 7556220,
          "model": "kettle",
          "visibility_ratio": 1.0,
          "occlusion_ratio": 1.0
        }
      ]
    },
    {
      "file": "5074546_facing_west.png",
      "cam_id": "5074546",
      "pos": {
        "x": -1.0,
        "y": 0.8,
        "z": 2.0
      },
      "direction": "west",
      "object_ratios": []
    },
    {
      "file": "7556220_facing_north.png",
      "cam_id": "7556220",
      "pos": {
        "x": -1,
        "y": 0.8,
        "z": -1
      },
      "direction": "north",
      "object_ratios": [
        {
          "object_id": 2132015,
          "model": "wood_chair",
          "visibility_ratio": 1.0,
          "occlusion_ratio": 1.0
        },
        {
          "object_id": 5074546,
          "model": "ligne_roset_armchair",
          "visibility_ratio": 1.0,
          "occlusion_ratio": 1.0
        }
      ]
    },
    {
      "file": "7556220_facing_east.png",
      "cam_id": "7556220",
      "pos": {
        "x": -1,
        "y": 0.8,
        "z": -1
      },
      "direction": "east",
      "object_ratios": []
    },
    {
      "file": "7556220_facing_south.png",
      "cam_id": "7556220",
      "pos": {
        "x": -1,
        "y": 0.8,
        "z": -1
      },
      "direction": "south",
      "object_ratios": []
    },
    {
      "file": "7556220_facing_west.png",
      "cam_id": "7556220",
      "pos": {
        "x": -1,
        "y": 0.8,
        "z": -1
      },
      "direction": "west",
      "object_ratios": []
    }
  ],
  "agent": {
    "direction": "north"
  }
}