{
  "room_size": [
    6,
    6
  ],
  "screen_size": [
    512,
    512
  ],
  "seed": 424,
  "min_distance": 0.3,
  "objects": [
    {
      "object_id": 4064323,
      "model": "wood_chair",
      "name": "wooden chair",
      "pos": {
        "x": 0,
        "y": 0,
        "z": 0
      },
      "rot": {
        "x": 0,
        "y": 90,
        "z": 0
      },
      "size": [
        0.4298932,
        0.47789539999999997
      ],
      "attributes": {
        "scale": 1.0,
        "has_orientation": true,
        "orientation": "east"
      }
    },
    {
      "object_id": 8945879,
      "model": "cabinet_24_wood_beach_honey",
      "name": "wooden cabinet",
      "pos": {
        "x": 1.0,
        "y": 0,
        "z": -2.0
      },
      "rot": {
        "x": 0,
        "y": 0,
        "z": 0
      },
      "size": [
        0.6073107,
        0.6424497
      ],
      "attributes": {
        "scale": 1.0,
        "has_orientation": false
      }
    },
    {
      "object_id": 7138793,
      "model": "5ft_wood_shelving",
      "name": "shelf",
      "pos": {
        "x": 1,
        "y": 0,
        "z": 0
      },
      "rot": {
        "x": 0,
        "y": 0,
        "z": 0
      },
      "size": [
        0.3857705,
        0.9451682
      ],
      "attributes": {
        "scale": 1.0,
        "has_orientation": false
      }
    }
  ],
  "cameras": [
    {
      "id": "agent",
      "label": "A",
      "position": {
        "x": -2,
        "y": 0.8,
        "z": 0
      },
      "rotation": {
        "y": 90.0
      }
    },
    {
      "id": "4064323",
      "label": "1",
      "position": {
        "x": 0,
        "y": 0.8,
        "z": 0
      },
      "rotation": {
        "y": 0.0
      }
    },
    {
      "id": "8945879",
      "label": "2",
      "position": {
        "x": 1.0,
        "y": 0.8,
        "z": -2.0
      },
      "rotation": {
        "y": -26.56505117707799
      }
    },
    {
      "id": "7138793",
      "label": "3",
      "position": {
        "x": 1,
        "y": 0.8,
        "z": 0
      },
      "rotation": {
        "y": -90.0
      }
    }
  ],
  "images": [
    {
      "file": "agent_facing_north.png",
      "cam_id": "agent",
      "pos": {
        "x": -2,
        "y": 0.8,
        "z": 0
      },
      "direction": "north",
      "object_ratios": []
    },
    {
      "file": "agent_facing_east.png",
      "cam_id": "agent",
      "pos": {
        "x": -2,
        "y": 0.8,
        "z": 0
      },
      "direction": "east",
      "object_ratios": [
        {
          "object_id": 4064323,
          "model": "wood_chair",
          "visibility_ratio": 1.0,
          "occlusion_ratio": 1.0
        },
        {
          "object_id": 8945879,
          "model": "cabinet_24_wood_beach_honey",
          "visibility_ratio": 1.0,
          "occlusion_ratio": 1.0
        },
        {
          "object_id": 7138793,
          "model": "5ft_wood_shelving",
          "visibility_ratio": 1.0,
          "occlusion_ratio": 1.0
        }
      ]
    },
    {
      "file": "agent_facing_south.png",
      "cam_id": "agent",
      "pos": {
        "x": -2,
        "y": 0.8,
        "z": 0
      },
      "direction": "south",
      "object_ratios": []
    },
    {
      "file": "agent_facing_west.png",
      "cam_id": "agent",
      "pos": {
        "x": -2,
        "y": 0.8,
        "z": 0
      },
      "direction": "west",
      "object_ratios": []
    },
    {
      "file": "4064323_facing_north.png",
      "cam_id": "4064323",
      "pos": {
        "x": 0,
        "y": 0.8,
        "z": 0
      },
      "direction": "north",
      "object_ratios": []
    },
    {
      "file": "4064323_facing_east.png",
      "cam_id": "4064323",
      "pos": {
        "x": 0,
        "y": 0.8,
        "z": 0
      },
      "direction": "east",
      "object_ratios": [
        {
          "object_id": 7138793,
          "model": "5ft_wood_shelving",
          "visibility_ratio": 1.0,
          "occlusion_ratio": 1.0
        }
      ]
    },
    {
      "file": "4064323_facing_south.png",
      "cam_id": "4064323",
      "pos": {
        "x": 0,
        "y": 0.8,
        "z": 0
      },
      "direction": "south",
      "object_ratios": [
        {
          "object_id": 8945879,
          "model": "cabinet_24_wood_beach_honey",
          "visibility_ratio": 1.0,
          "occlusion_ratio": 1.0
        }
      ]
    },
    {
      "file": "4064323_facing_west.png",
      "cam_id": "4064323",
      "pos": {
        "x": 0,
        "y": 0.8,
        "z": 0
      },
      "direction": "west",
      "object_ratios": []
    },
    {
      "file": "8945879_facing_north.png",
      "cam_id": "8945879",
      "pos": {
        "x": 1.0,
        "y": 0.8,
        "z": -2.0
      },
      "direction": "north",
      "object_ratios": [
        {
          "object_id": 4064323,
          "model": "wood_chair",
          "visibility_ratio": 1.0,
          "occlusion_ratio": 1.0
        },
        {
          "object_id": 7138793,
          "model": "5ft_wood_shelving",
          "visibility_ratio": 1.0,
          "occlusion_ratio": 1.0
        }
      ]
    },
    {
      "file": "8945879_facing_east.png",
      "cam_id": "8945879",
      "pos": {
        "x": 1.0,
        "y": 0.8,
        "z": -2.0
      },
      "direction": "east",
      "object_ratios": []
    },
    {
      "file": "8945879_facing_south.png",
      "cam_id": "8945879",
      "pos": {
        "x": 1.0,
        "y": 0.8,
        "z": -2.0
      },
      "direction": "south",
      "object_ratios": []
    },
    {
      "file": "8945879_facing_west.png",
      "cam_id": "8945879",
      "pos": {
        "x": 1.0,
        "y": 0.8,
        "z": -2.0
      },
      "direction": "west",
      "object_ratios": []
    },
    {
      "file": "7138793_facing_north.png",
      "cam_id": "7138793",
      "pos": {
        "x": 1,
        "y": 0.8,
        "z": 0
      },
      "direction": "north",
      "object_ratios": []
    },
    {
      "file": "7138793_facing_east.png",
      "cam_id": "7138793",
      "pos": {
        "x": 1,
        "y": 0.8,
        "z": 0
      },
      "direction": "east",
      "object_ratios": []
    },
    {
      "file": "7138793_facing_south.png",
      "cam_id": "7138793",
      "pos": {
        "x": 1,
        "y": 0.8,
        "z": 0
      },
      "direction": "south",
      "object_ratios": [
        {
          "object_id": 8945879,
          "model": "cabinet_24_wood_beach_honey",
          "visibility_ratio": 1.0,
          "occlusion_ratio": 1.0
        }
      ]
    },
    {
      "file": "7138793_facing_west.png",
      "cam_id": "7138793",
      "pos": {
        "x": 1,
        "y": 0.8,
        "z": 0
      },
      "direction": "west",
      "object_ratios": [
        {
          "object_id": 4064323,
          "model": "wood_chair",
          "visibility_ratio": 1.0,
          "occlusion_ratio": 1.0
        }
      ]
    }
  ],
  "agent": {
    "direction": "north"
  }
}