{
  "name": "room_setting",
  "objects": [
    {
      "name": "basket",
      "pos": [
        2.157397311510156,
        -2.60815310928656
      ],
      "ori": [
        1,
        0
      ]
    },
    {
      "name": "wooden table",
      "pos": [
        2.670436049291525,
        1.3699027396384322
      ],
      "ori": [
        0,
        1
      ]
    },
    {
      "name": "microwave",
      "pos": [
        -0.6264746120318558,
        0.9198957173987266
      ],
      "ori": [
        0,
        -1
      ]
    },
    {
      "name": "cam_1",
      "pos": [
        2.157397311510156,
        -2.60815310928656
      ],
      "ori": [
        1,
        0
      ]
    },
    {
      "name": "cam_2",
      "pos": [
        2.670436049291525,
        1.3699027396384322
      ],
      "ori": [
        0,
        -1
      ]
    },
    {
      "name": "cam_3",
      "pos": [
        -0.6264746120318558,
        0.9198957173987266
      ],
      "ori": [
        -1,
        0
      ]
    }
  ],
  "agent": {
    "name": "agent",
    "pos": [
      -1.1543957482667295,
      -0.6828159098272955
    ],
    "ori": [
      0,
      1
    ]
  },
  "all_objects": [
    {
      "name": "agent",
      "pos": [
        -1.1543957482667295,
        -0.6828159098272955
      ],
      "ori": [
        0,
        1
      ]
    },
    {
      "name": "basket",
      "pos": [
        2.157397311510156,
        -2.60815310928656
      ],
      "ori": [
        1,
        0
      ]
    },
    {
      "name": "wooden table",
      "pos": [
        2.670436049291525,
        1.3699027396384322
      ],
      "ori": [
        0,
        1
      ]
    },
    {
      "name": "microwave",
      "pos": [
        -0.6264746120318558,
        0.9198957173987266
      ],
      "ori": [
        0,
        -1
      ]
    },
    {
      "name": "cam_1",
      "pos": [
        2.157397311510156,
        -2.60815310928656
      ],
      "ori": [
        1,
        0
      ]
    },
    {
      "name": "cam_2",
      "pos": [
        2.670436049291525,
        1.3699027396384322
      ],
      "ori": [
        0,
        -1
      ]
    },
    {
      "name": "cam_3",
      "pos": [
        -0.6264746120318558,
        0.9198957173987266
      ],
      "ori": [
        -1,
        0
      ]
    }
  ]
}