{
  "name": "room_setting",
  "objects": [
    {
      "name": "blue chair",
      "pos": [
        0,
        -1
      ],
      "ori": [
        0,
        -1
      ]
    },
    {
      "name": "green chair",
      "pos": [
        3.0,
        0.0
      ],
      "ori": [
        1,
        0
      ]
    },
    {
      "name": "yellow chair",
      "pos": [
        0,
        2
      ],
      "ori": [
        -1,
        0
      ]
    },
    {
      "name": "wooden table",
      "pos": [
        -2.0,
        -1.0
      ],
      "ori": [
        0,
        1
      ]
    },
    {
      "name": "cam_1",
      "pos": [
        0,
        -1
      ],
      "ori": [
        1,
        0
      ]
    },
    {
      "name": "cam_2",
      "pos": [
        3.0,
        0.0
      ],
      "ori": [
        0,
        -1
      ]
    },
    {
      "name": "cam_3",
      "pos": [
        0,
        2
      ],
      "ori": [
        -1,
        0
      ]
    },
    {
      "name": "cam_4",
      "pos": [
        -2.0,
        -1.0
      ],
      "ori": [
        0,
        1
      ]
    }
  ],
  "agent": {
    "name": "agent",
    "pos": [
      2,
      2
    ],
    "ori": [
      -1,
      0
    ]
  },
  "all_objects": [
    {
      "name": "agent",
      "pos": [
        2,
        2
      ],
      "ori": [
        -1,
        0
      ]
    },
    {
      "name": "blue chair",
      "pos": [
        0,
        -1
      ],
      "ori": [
        0,
        -1
      ]
    },
    {
      "name": "green chair",
      "pos": [
        3.0,
        0.0
      ],
      "ori": [
        1,
        0
      ]
    },
    {
      "name": "yellow chair",
      "pos": [
        0,
        2
      ],
      "ori": [
        -1,
        0
      ]
    },
    {
      "name": "wooden table",
      "pos": [
        -2.0,
        -1.0
      ],
      "ori": [
        0,
        1
      ]
    },
    {
      "name": "cam_1",
      "pos": [
        0,
        -1
      ],
      "ori": [
        1,
        0
      ]
    },
    {
      "name": "cam_2",
      "pos": [
        3.0,
        0.0
      ],
      "ori": [
        0,
        -1
      ]
    },
    {
      "name": "cam_3",
      "pos": [
        0,
        2
      ],
      "ori": [
        -1,
        0
      ]
    },
    {
      "name": "cam_4",
      "pos": [
        -2.0,
        -1.0
      ],
      "ori": [
        0,
        1
      ]
    }
  ]
}